README.md
invokr.py
pyproject.toml
setup.cfg
setup.py
invokust/__init__.py
invokust/loadtest.py
invokust/settings.py
invokust/aws_lambda/__init__.py
invokust/aws_lambda/lambda_load_test.py
invokust/aws_lambda/results_aggregator.py
invokust/aws_lambda/runtime_info.py
invokust_tmp.egg-info/PKG-INFO
invokust_tmp.egg-info/SOURCES.txt
invokust_tmp.egg-info/dependency_links.txt
invokust_tmp.egg-info/requires.txt
invokust_tmp.egg-info/top_level.txt