Metadata-Version: 2.1
Name: invokust-tmp
Version: 0.76
Summary: A small wrapper for locust to allow running load tests from within Python or on AWS Lambda
Home-page: https://github.com/FutureSharks/invokust
Author: Max Williams
Author-email: futuresharks@gmail.com
License: MIT
Download-URL: https://github.com/FutureSharks/invokust/archive/0.76.tar.gz
Keywords: testing,loadtest,lambda,locust
Platform: UNKNOWN
Classifier: Topic :: Software Development :: Quality Assurance
Classifier: Topic :: Software Development :: Testing
Classifier: Topic :: Software Development :: Testing :: Traffic Generation
Classifier: Programming Language :: Python :: 3.6
